CHANGELOG.rst
MANIFEST.in
README.rst
setup.py
pyagar/__init__.py
pyagar/client.py
pyagar/cmdline.py
pyagar/control.py
pyagar/log.py
pyagar/messages.py
pyagar/visual.py
pyagar.egg-info/PKG-INFO
pyagar.egg-info/SOURCES.txt
pyagar.egg-info/dependency_links.txt
pyagar.egg-info/entry_points.txt
pyagar.egg-info/not-zip-safe
pyagar.egg-info/requires.txt
pyagar.egg-info/top_level.txt
pyagar/static/Ubuntu-R.ttf
pyagar/static/ubuntu-font-licence-1.0.txt