Metadata-Version: 1.1
Name: pyagar
Version: 0.0.7
Summary: agar.io python client library
Home-page: https://github.com/nilp0inter/pyagar
Author: Roberto Abdelkader Martínez Pérez
Author-email: robertomartinezp@gmail.com
License: LGPLv3
Keywords: agar.io client
Platform: UNKNOWN
Classifier: Programming Language :: Python :: 3.4
Classifier: Development Status :: 4 - Beta
Classifier: License :: OSI Approved :: GNU Lesser General Public License v3 (LGPLv3)
